git_index_parser/__init__.py
git_index_parser/git_index_file.py
git_index_parser/git_index_file_entry.py
git_index_parser/git_index_file_extension.py
git_index_parser/parser.py
git_index_parser-1.0.0.dist-info/LICENSE
git_index_parser-1.0.0.dist-info/METADATA
git_index_parser-1.0.0.dist-info/WHEEL
git_index_parser-1.0.0.dist-info/top_level.txt
git_index_parser-1.0.0.dist-info/RECORD
