Metadata-Version: 2.1
Name: git-index-parser
Version: 1.0.0
Summary: A package to parse the index file of a git repository
Home-page: https://github.com/wahlflo/GitIndexFileParser
Author: Florian Wahl
Author-email: florian.wahl.developer@gmail.com
License: UNKNOWN
Platform: UNKNOWN
Classifier: Programming Language :: Python :: 3
Classifier: License :: OSI Approved :: MIT License
License-File: LICENSE
